GoodByeCorona/Corona.py
GoodByeCorona/__init__.py
GoodByeCorona-1.0.dist-info/METADATA
GoodByeCorona-1.0.dist-info/WHEEL
GoodByeCorona-1.0.dist-info/top_level.txt
GoodByeCorona-1.0.dist-info/RECORD
