Metadata-Version: 2.1
Name: GoodByeCorona
Version: 1.0
Summary: 굿바이코로나 Api를 가볍게 사용하기 위해 모듈로 제작하였습니다.
Home-page: https://github.com/UniqueDevStorm/GoodByeCorona
Author: UniqueDevStorm
Author-email: storm@uniquecode.team
License: MIT
Platform: UNKNOWN
Classifier: Programming Language :: Python :: 3
Classifier: License :: OSI Approved :: MIT License
Classifier: Operating System :: OS Independent
